dbt_junit_report/.python-version
dbt_junit_report/__init__.py
dbt_junit_report/dbt_junit_report.py
dbt_junit_report/tests/__init__.py
dbt_junit_report/tests/test_dbt_junit_report.py
dbt_junit_report-1.0.12.dist-info/METADATA
dbt_junit_report-1.0.12.dist-info/WHEEL
dbt_junit_report-1.0.12.dist-info/entry_points.txt
dbt_junit_report-1.0.12.dist-info/licenses/LICENSE
dbt_junit_report-1.0.12.dist-info/RECORD
