Metadata-Version: 2.4
Name: dbt-junit-report
Version: 1.0.12
Summary: Convert `dbt` run results into a JUnit report format
Project-URL: Homepage, https://gitlab.com/cedric3.olivier/dbt_junit_report
Project-URL: Issues, https://gitlab.com/cedric3.olivier/dbt_junit_report/-/issues
Author-email: Cedric OLIVIER <cedric3.olivier@orange.com>
License-File: LICENSE
Classifier: License :: OSI Approved :: MIT License
Classifier: Operating System :: OS Independent
Classifier: Programming Language :: Python :: 3
Requires-Python: >=3.8
Requires-Dist: junit-xml>=1.9
Requires-Dist: pytest-mock>=3.14.0
